biobertology/__init__.py
biobertology/biobert.py
biobertology/download.py
biobert_pytorch-0.9.dist-info/LICENSE
biobert_pytorch-0.9.dist-info/METADATA
biobert_pytorch-0.9.dist-info/WHEEL
biobert_pytorch-0.9.dist-info/top_level.txt
biobert_pytorch-0.9.dist-info/RECORD
