Metadata-Version: 2.1
Name: biobert-pytorch
Version: 0.9
Summary: Ready to use BioBert pytorch weights for HuggingFace pytorch BertModel.
Home-page: https://github.com/jgamper/biobert-pytorch
Author: Jevgenij Gamper
Author-email: jevgenij.gamper5@gmail.com
License: UNKNOWN
Platform: UNKNOWN
Classifier: Programming Language :: Python :: 3.6
